deming/__init__.py
deming-0.1.3.dist-info/LICENSE
deming-0.1.3.dist-info/METADATA
deming-0.1.3.dist-info/WHEEL
deming-0.1.3.dist-info/RECORD
