Metadata-Version: 2.1
Name: deming
Version: 0.1.3
Summary: W Edwards Deming Quality Control Charts
License: MIT
Author: Abhi Yerra
Author-email: abhi@opszero.comt
Requires-Python: >=3.11,<4.0
Classifier: License :: OSI Approved :: MIT License
Classifier: Programming Language :: Python :: 3
Classifier: Programming Language :: Python :: 3.11
Classifier: Programming Language :: Python :: 3.12
Requires-Dist: matplotlib (>=3.8.4,<4.0.0)
